src/__init__.py
src/_version.py
src/lrn_cli.py
lrn_cli-1.0.0.dist-info/LICENSE.md
lrn_cli-1.0.0.dist-info/METADATA
lrn_cli-1.0.0.dist-info/WHEEL
lrn_cli-1.0.0.dist-info/entry_points.txt
lrn_cli-1.0.0.dist-info/top_level.txt
lrn_cli-1.0.0.dist-info/RECORD
