Metadata-Version: 2.1
Name: lrn_cli
Version: 1.0.0
Summary: Learnosity CLI tool
Author-email: Olivier Mehani <olivier.mehani@learnosity.com>
Requires-Python: >=3.9
License-File: LICENSE.md
Requires-Dist: click >=7
Requires-Dist: learnosity-sdk
Requires-Dist: pygments >=2
Requires-Dist: requests ~=2.31.0
Requires-Dist: urllib3 ~=2.2.0
Provides-Extra: dev
Requires-Dist: build ; extra == 'dev'
Requires-Dist: setuptools ; extra == 'dev'
Requires-Dist: twine ; extra == 'dev'
Requires-Dist: wheel ; extra == 'dev'
Provides-Extra: test
Requires-Dist: black ; extra == 'test'
Requires-Dist: isort ; extra == 'test'
Requires-Dist: pytest ~=7.4.3 ; extra == 'test'
Requires-Dist: pytest-black ; extra == 'test'
Requires-Dist: pytest-isort ; extra == 'test'
Requires-Dist: pytest-runner ; extra == 'test'
Provides-Extra: trogon
Requires-Dist: trogon ; extra == 'trogon'
